pyprofilers/__about__.py
pyprofilers/__init__.py
pyprofilers/pyprofilers.py
pyprofilers-0.1.dist-info/LICENSE
pyprofilers-0.1.dist-info/METADATA
pyprofilers-0.1.dist-info/WHEEL
pyprofilers-0.1.dist-info/top_level.txt
pyprofilers-0.1.dist-info/RECORD
