Metadata-Version: 2.1
Name: pyprofilers
Version: 0.1
Summary: A convenient wrapper library for different Python profilers.
Home-page: https://github.com/andreasfelix/pyprofilers
Author: Felix Andreas
Author-email: UNKNOWN
License: UNKNOWN
Platform: UNKNOWN
Requires-Dist: line-profiler
Requires-Dist: yappi
